coderoast/__init__.py
coderoast/core.py
coderoast/handlers.py
coderoast/insults.py
coderoast-0.2.0.dist-info/licenses/LICENSE
tests/__init__.py
tests/test_coderoast.py
coderoast-0.2.0.dist-info/METADATA
coderoast-0.2.0.dist-info/WHEEL
coderoast-0.2.0.dist-info/top_level.txt
coderoast-0.2.0.dist-info/RECORD
